repobee_plug/__init__.py
repobee_plug/__version.py
repobee_plug/_apimeta.py
repobee_plug/_containers.py
repobee_plug/_corehooks.py
repobee_plug/_deprecation.py
repobee_plug/_exceptions.py
repobee_plug/_exthooks.py
repobee_plug/_name.py
repobee_plug/_pluginmeta.py
repobee_plug/_serialize.py
repobee_plug/_tasks.py
repobee_plug-0.12.0.dist-info/LICENSE
repobee_plug-0.12.0.dist-info/METADATA
repobee_plug-0.12.0.dist-info/WHEEL
repobee_plug-0.12.0.dist-info/top_level.txt
repobee_plug-0.12.0.dist-info/RECORD
