Metadata-Version: 2.1
Name: repobee-plug
Version: 0.12.0
Summary: Core components for plugin system in repobee
Home-page: https://github.com/repobee/repobee-plug
Author: Simon Larsén
Author-email: slarse@kth.se
License: MIT
Download-URL: https://github.com/repobee/repobee-plug/archive/v0.12.0.tar.gz
Platform: UNKNOWN
Classifier: Development Status :: 3 - Alpha
Classifier: Intended Audience :: Education
Classifier: Programming Language :: Python :: 3.5
Classifier: Programming Language :: Python :: 3.6
Classifier: Programming Language :: Python :: 3.7
Classifier: Programming Language :: Python :: Implementation :: CPython
Classifier: License :: OSI Approved :: MIT License
Classifier: Operating System :: POSIX
Requires-Dist: pluggy (>=0.13.1)
Requires-Dist: daiquiri
Provides-Extra: test
Requires-Dist: pytest (>=4.0.0) ; extra == 'test'
Requires-Dist: pytest-cov ; extra == 'test'
Requires-Dist: codecov ; extra == 'test'
Requires-Dist: tox ; extra == 'test'
